autoconf/__init__.py
autoconf/class_path.py
autoconf/conf.py
autoconf/dictable.py
autoconf/directory_config.py
autoconf/exc.py
autoconf/fitsable.py
autoconf/jax_wrapper.py
autoconf/output.py
autoconf/setup_colab.py
autoconf/json_prior/__init__.py
autoconf/json_prior/config.py
autoconf/json_prior/generate.py
autoconf/mock/__init__.py
autoconf/mock/mock_real.py
autoconf/tools/__init__.py
autoconf/tools/decorators.py
autoconf-2026.1.21.3.dist-info/licenses/LICENSE
priors/subconfig.json
scripts/convert_config.py
scripts/convert_prior_configs.py
scripts/edenise.py
scripts/generate_priors.py
autoconf-2026.1.21.3.dist-info/METADATA
autoconf-2026.1.21.3.dist-info/WHEEL
autoconf-2026.1.21.3.dist-info/top_level.txt
autoconf-2026.1.21.3.dist-info/RECORD
